libpythonpro_tardelli/__init__.py
libpythonpro_tardelli/github_api.py
libpythonpro_tardelli-0.1.dist-info/LICENSE
libpythonpro_tardelli-0.1.dist-info/METADATA
libpythonpro_tardelli-0.1.dist-info/WHEEL
libpythonpro_tardelli-0.1.dist-info/top_level.txt
libpythonpro_tardelli-0.1.dist-info/RECORD
